{
  "doc_id": "1320-19",
  "filename": "1320-19.pdf",
  "extraction_date": "2025-11-17T10:41:41.884957",
  "extraction_method": "pdfplumber",
  "document_types": [
    "legal_document",
    "correspondence"
  ],
  "text_length": 33018,
  "images_extracted": 0,
  "dates_found": 1,
  "people_found": 23,
  "locations_found": 4,
  "linked_emails": [],
  "dates": [
    {
      "date_string": "01/03/24",
      "position": 46
    }
  ],
  "people": [
    "Joinder In Action",
    "So Glenn",
    "Including Mr",
    "New Mexico",
    "Ghislaine Maxwell",
    "Virgin Islands",
    "Growing Together",
    "Prince Andrew",
    "Luc Brunel",
    "Jane Doe",
    "Jean Luc Brunel",
    "Sharon Churcher",
    "When Ghislaine Maxwell",
    "Glenn Dubin",
    "El Brillo",
    "Jeffrey Epstein",
    "Corrected Motion Pursuant",
    "Marvin Minsky",
    "In Sydney",
    "What Growing Together"
  ],
  "locations": [
    "Virgin Islands",
    "Palm Beach",
    "France",
    "New Mexico"
  ],
  "images": []
}