{
  "doc_id": "1325-17",
  "filename": "1325-17.pdf",
  "extraction_date": "2025-11-17T10:43:11.376250",
  "extraction_method": "pdfplumber",
  "document_types": [
    "deposition",
    "legal_document"
  ],
  "text_length": 9953,
  "images_extracted": 0,
  "dates_found": 17,
  "people_found": 27,
  "locations_found": 3,
  "linked_emails": [],
  "dates": [
    {
      "date_string": "01/04/24",
      "position": 46
    },
    {
      "date_string": "01/04/24",
      "position": 124
    },
    {
      "date_string": "01/04/24",
      "position": 947
    },
    {
      "date_string": "01/04/24",
      "position": 1665
    },
    {
      "date_string": "01/04/24",
      "position": 2752
    },
    {
      "date_string": "01/04/24",
      "position": 4028
    },
    {
      "date_string": "01/04/24",
      "position": 5124
    },
    {
      "date_string": "01/04/24",
      "position": 6088
    },
    {
      "date_string": "9/11/2001",
      "position": 6787
    },
    {
      "date_string": "01/04/24",
      "position": 7029
    }
  ],
  "people": [
    "Notary Public",
    "Survivors Charter",
    "Esquire\nHaddon",
    "One Florida Park",
    "Royal Palm Beach",
    "Wellington High School",
    "Florida Professional Reporter",
    "West Palm",
    "Jenny Martin",
    "Royal Palm",
    "South Area",
    "Survivors Charter School",
    "Court Reporter",
    "Paul Katz Professional",
    "Esquire\nFarmer",
    "Palm Beach High",
    "Tony Figueroa",
    "Palm Coast",
    "Drive South",
    "Video Deposition"
  ],
  "locations": [
    "New York",
    "Palm Beach",
    "Florida"
  ],
  "images": []
}